{
  "project_name": "CXL_Switch_SoP_1TB",
  "reach_mm": 300.0,
  "loss_db": 18.0,
  "target_bandwidth_gbps": 224.0,
  "max_power_budget_w": 200.0,
  "packaging": {
    "topology": "Face_to_Face",
    "material_name": "Megtron7",
    "interposer": "Silicon_Interposer"
  },
  "die_hierarchy": {
    "die_0": {
      "name": "CXL_Switch_Logic",
      "type": "3nm_FinFET",
      "size_mm": [
        15,
        15
      ]
    },
    "die_1": {
      "name": "SRAM_Search_Die",
      "type": "Stacked_SRAM",
      "size_mm": [
        12,
        12
      ]
    }
  },
  "voxel_stack_params": {
    "layers": 5,
    "grid_size": 16,
    "k_map": {
      "Die": 140.0,
      "Metal_Stack": 380.0,
      "C4_BGA": 50.0,
      "Package": 0.3
    }
  },
  "constraints": {
    "min_isolation_db": 40,
    "reliability_years": 10,
    "fec_preference": "inner",
    "modulation": "PAM4"
  },
  "reach_classification": "MR",
  "architectural_recs": [
    "  -> Clocking: Drift detected. Use CDR (Adds ~15% area).",
    "  -> PHY: Analog FFE + DFE required for eye closure.",
    "  -> \ud83d\udd25 THERMAL ALERT: Material Wall reached. Switch to GaAs."
  ],
  "floorplan": {
    "lx": 9,
    "ly": 0,
    "mx": 6,
    "my": 11,
    "estimated_max_temp": 107.78971862792969,
    "internal_reach_mm": 1.4000000000000001
  },
  "si_signoff": {
    "total_insertion_loss_db": 145.57761698144628,
    "eye_width_ui": -1.9115523396289258,
    "eye_height_mv": 4.20929281388278e-05
  },
  "si_analysis_v3": {
    "loss": 37.02755905511811,
    "snr_margin_db": 2.472440944881889,
    "eye_width_ui": 0.12362204724409445,
    "status": "\u274c FAIL"
  }
}